wechatpayv3/__init__.py
wechatpayv3/apply4subject.py
wechatpayv3/applyment.py
wechatpayv3/businesscircle.py
wechatpayv3/capital.py
wechatpayv3/complaint.py
wechatpayv3/core.py
wechatpayv3/fapiao.py
wechatpayv3/goldplan.py
wechatpayv3/marketing.py
wechatpayv3/mchtransfer.py
wechatpayv3/media.py
wechatpayv3/merchantrisk.py
wechatpayv3/parking.py
wechatpayv3/payscore.py
wechatpayv3/profitsharing.py
wechatpayv3/smartguide.py
wechatpayv3/transaction.py
wechatpayv3/transfer.py
wechatpayv3/type.py
wechatpayv3/utils.py
wechatpayv3/async_/__init__.py
wechatpayv3/async_/apply4subject.py
wechatpayv3/async_/applyment.py
wechatpayv3/async_/businesscircle.py
wechatpayv3/async_/capital.py
wechatpayv3/async_/complaint.py
wechatpayv3/async_/core.py
wechatpayv3/async_/fapiao.py
wechatpayv3/async_/goldplan.py
wechatpayv3/async_/marketing.py
wechatpayv3/async_/mchtransfer.py
wechatpayv3/async_/media.py
wechatpayv3/async_/merchantrisk.py
wechatpayv3/async_/parking.py
wechatpayv3/async_/payscore.py
wechatpayv3/async_/profitsharing.py
wechatpayv3/async_/smartguide.py
wechatpayv3/async_/transaction.py
wechatpayv3/async_/transfer.py
wechatpayv3/async_/type.py
wechatpayv3/async_/utils.py
wechatpayv3-2.0.1.dist-info/licenses/LICENSE
wechatpayv3-2.0.1.dist-info/METADATA
wechatpayv3-2.0.1.dist-info/WHEEL
wechatpayv3-2.0.1.dist-info/top_level.txt
wechatpayv3-2.0.1.dist-info/RECORD
