Metadata-Version: 2.4
Name: wechatpayv3
Version: 2.0.1
Summary: 微信支付 Python SDK(python sdk for wechatpay)
Home-page: https://github.com/minibear2021/wechatpayv3
Author: minibear
Author-email: 321983@qq.com
License: MIT
Keywords: python sdk wechatpay api v3 微信支付
Classifier: Development Status :: 5 - Production/Stable
Classifier: Topic :: Office/Business :: Financial
Classifier: Programming Language :: Python :: 3
License-File: LICENSE
Requires-Dist: requests>=2.21.0
Requires-Dist: cryptography>=35.0.0
Provides-Extra: async
Requires-Dist: httpx>=0.28.1; extra == "async"
Requires-Dist: aiofiles>=23.2.0; extra == "async"
Dynamic: author
Dynamic: author-email
Dynamic: classifier
Dynamic: description
Dynamic: description-content-type
Dynamic: home-page
Dynamic: keywords
Dynamic: license
Dynamic: license-file
Dynamic: provides-extra
Dynamic: requires-dist
Dynamic: summary
